photomosaic/__init__.py
photomosaic/_version.py
photomosaic/flickr.py
photomosaic/parallel.py
photomosaic/photomosaic.py
photomosaic-0.3.1.dist-info/METADATA
photomosaic-0.3.1.dist-info/RECORD
photomosaic-0.3.1.dist-info/WHEEL
photomosaic-0.3.1.dist-info/top_level.txt
