Metadata-Version: 2.1
Name: photomosaic
Version: 0.3.1
Summary: Assemble thumbnail-sized images from a large collection into a tiling
Home-page: https://github.com/danielballan/photomosaic
Author: Photomosiac Contributors
Author-email: daniel.b.allan@gmail.com
License: BSD 3-Clause
Keywords: art image color mosaic
Platform: UNKNOWN
Classifier: Development Status :: 3 - Alpha
Classifier: Intended Audience :: Developers
Classifier: License :: OSI Approved :: BSD License
Classifier: Programming Language :: Python :: 3
Classifier: Programming Language :: Python :: 3.4
Classifier: Programming Language :: Python :: 3.5
Provides-Extra: parallel
Provides-Extra: complete
Requires-Dist: colorspacious
Requires-Dist: matplotlib
Requires-Dist: numpy
Requires-Dist: requests
Requires-Dist: scikit-image
Requires-Dist: scipy
Requires-Dist: tqdm
Provides-Extra: complete
Requires-Dist: dask[bag]; extra == 'complete'
Provides-Extra: parallel
Requires-Dist: dask[bag]; extra == 'parallel'
